revents/__init__.py
revents/test.py
revents-0.0.6.dist-info/LICENSE
revents-0.0.6.dist-info/METADATA
revents-0.0.6.dist-info/WHEEL
revents-0.0.6.dist-info/top_level.txt
revents-0.0.6.dist-info/RECORD
