Metadata-Version: 2.1
Name: revents
Version: 0.0.6
Summary: Reddit events for asyncpraw
Home-page: https://github.com/YodaPY/revents
Author: YodaPY
License: UNKNOWN
Platform: UNKNOWN
Classifier: Development Status :: 4 - Beta
Classifier: Intended Audience :: Developers
Classifier: Natural Language :: English
Classifier: Programming Language :: Python :: 3.7
Classifier: Programming Language :: Python :: 3.8
Classifier: Programming Language :: Python :: 3.9
Classifier: Programming Language :: Python :: Implementation :: CPython
Classifier: Programming Language :: Python :: 3 :: Only
Requires-Python: >=3.7.0,<3.10
Requires-Dist: asyncpraw
